[{"id":1,"rentalDate":"2022-03-30T22:18:23.394Z","returnDate":"2022-04-06T22:18:23.391Z","userId":4,"monkeyId":2,"active":false},{"id":2,"rentalDate":"2022-03-30T22:22:13.474Z","returnDate":"2022-04-06T22:22:13.474Z","userId":4,"monkeyId":2,"active":false},{"id":3,"rentalDate":"2022-03-30T22:32:01.961Z","returnDate":"2022-04-06T22:32:01.961Z","userId":4,"monkeyId":2,"active":false},{"id":4,"rentalDate":"2022-03-30T22:35:25.880Z","returnDate":"2022-04-06T22:35:25.880Z","userId":4,"monkeyId":2,"active":true},{"id":5,"rentalDate":"2022-03-30T22:39:46.817Z","returnDate":"2022-04-06T22:39:46.817Z","userId":4,"monkeyId":2,"active":true},{"id":6,"rentalDate":"2022-03-31T02:27:24.741Z","returnDate":"2022-04-07T02:27:24.741Z","userId":4,"monkeyId":5,"active":false}]